__version__.py
loopytimer.py
loopytimer-0.1.0.dist-info/DESCRIPTION.rst
loopytimer-0.1.0.dist-info/METADATA
loopytimer-0.1.0.dist-info/RECORD
loopytimer-0.1.0.dist-info/WHEEL
loopytimer-0.1.0.dist-info/metadata.json
loopytimer-0.1.0.dist-info/top_level.txt
