Metadata-Version: 2.0
Name: loopytimer
Version: 0.1.0
Summary: A loop timer instead of default one shot Timer from threading. Base on pythonTimer created by terryltang.
Home-page: https://github.com/wavky/loopytimer
Author: Wavky
Author-email: master@wavky.com
License: MIT
Platform: UNKNOWN
Classifier: License :: OSI Approved :: MIT License
Classifier: Programming Language :: Python
Classifier: Programming Language :: Python :: 2.6
Classifier: Programming Language :: Python :: 2.7
Classifier: Programming Language :: Python :: 3
Classifier: Programming Language :: Python :: 3.3
Classifier: Programming Language :: Python :: 3.4
Classifier: Programming Language :: Python :: 3.5
Classifier: Programming Language :: Python :: 3.6
Classifier: Programming Language :: Python :: Implementation :: CPython
Classifier: Programming Language :: Python :: Implementation :: PyPy
